pypi2nix/VERSION
pypi2nix/__init__.py
pypi2nix/_version.py
pypi2nix/archive.py
pypi2nix/cli.py
pypi2nix/configuration.py
pypi2nix/environment_marker.py
pypi2nix/exceptions.py
pypi2nix/license.py
pypi2nix/logger.py
pypi2nix/main.py
pypi2nix/memoize.py
pypi2nix/nix.py
pypi2nix/overrides.py
pypi2nix/package_source.py
pypi2nix/project_directory.py
pypi2nix/pypi.py
pypi2nix/pypi_package.py
pypi2nix/pypi_release.py
pypi2nix/python_version.py
pypi2nix/requirement_parser.py
pypi2nix/requirement_parser_grammar.py
pypi2nix/requirement_set.py
pypi2nix/requirements.py
pypi2nix/requirements_collector.py
pypi2nix/requirements_file.py
pypi2nix/source_distribution.py
pypi2nix/sources.py
pypi2nix/stage1.py
pypi2nix/stage2.py
pypi2nix/stage3.py
pypi2nix/target_platform.py
pypi2nix/utils.py
pypi2nix/version.py
pypi2nix/wheel.py
pypi2nix/package/__init__.py
pypi2nix/package/exceptions.py
pypi2nix/package/interfaces.py
pypi2nix/package/metadata.py
pypi2nix/package/pyproject.py
pypi2nix/package/setupcfg.py
pypi2nix/pip/__init__.py
pypi2nix/pip/base.nix
pypi2nix/pip/bootstrap.nix
pypi2nix/pip/download.nix
pypi2nix/pip/exceptions.py
pypi2nix/pip/implementation.py
pypi2nix/pip/install.nix
pypi2nix/pip/interface.py
pypi2nix/pip/virtualenv.py
pypi2nix/pip/wheel.nix
pypi2nix/templates/generated.nix.j2
pypi2nix/templates/overrides.nix.j2
pypi2nix/templates/prefetch-github.nix.j2
pypi2nix/templates/requirements.nix.j2
pypi2nix/wheels/__init__.py
pypi2nix/wheels/index.json
pypi2nix/wheels/schema.py
pypi2nix-2.0.4.dist-info/METADATA
pypi2nix-2.0.4.dist-info/WHEEL
pypi2nix-2.0.4.dist-info/entry_points.txt
pypi2nix-2.0.4.dist-info/top_level.txt
pypi2nix-2.0.4.dist-info/RECORD
